vera/CCFs.py
vera/DACE.py
vera/HZ.py
vera/KOBE.py
vera/RV.py
vera/TESS.py
vera/__init__.py
vera/_actin.py
vera/_periodograms.py
vera/_plots.py
vera/_report.py
vera/binit.py
vera/cute_style.mplstyle
vera/gaia.py
vera/globals.py
vera/identifiers.py
vera/photometry.py
vera/query_ASASSN.py
vera/query_ESOarchive.py
vera/query_dace.py
vera/query_periods.py
vera/query_simbad.py
vera/query_superWASP.py
vera/spectra.py
vera/stat_tools.py
vera/utils.py
vera/visibility.py
verapy-0.0.5.dist-info/LICENSE
verapy-0.0.5.dist-info/METADATA
verapy-0.0.5.dist-info/WHEEL
verapy-0.0.5.dist-info/dependency_links.txt
verapy-0.0.5.dist-info/top_level.txt
verapy-0.0.5.dist-info/RECORD
