Metadata-Version: 2.1
Name: verapy
Version: 0.0.5
Summary: velocidades radiais
Home-page: https://github.com/j-faria/vera
Author: João Faria
Author-email: joao.faria@astro.up.pt
License: UNKNOWN
Platform: UNKNOWN
Classifier: Development Status :: 4 - Beta
Classifier: License :: OSI Approved :: MIT License
Classifier: Programming Language :: Python :: 3
License-File: LICENSE
Requires-Dist: numpy
Requires-Dist: scipy
Requires-Dist: matplotlib
Requires-Dist: requests
Requires-Dist: tqdm
Requires-Dist: python-dace-client
Requires-Dist: cached-property
Requires-Dist: colorful
Requires-Dist: astropy
Requires-Dist: astroquery
Requires-Dist: lightkurve
Requires-Dist: gatspy
Requires-Dist: PyAstronomy
Requires-Dist: pyexoplaneteu
Requires-Dist: pyephem
Requires-Dist: mpldatacursor
Requires-Dist: iCCF
